scr/nor_1bit.v
module nor_1bit (
    input  A,
    input  B,
    output Y
);
    assign Y = ~(A | B); // NOR = negación del OR
endmodule

scr/nor_4bits.v
`include "nor_1bit.v"

module nor_4bits (
    input  [3:0] A,
    input  [3:0] B,
    output [3:0] Y
);

    // Instanciamos las 4 puertas NOR de 1 bit
    nor_1bit N0 (.A(A[0]), .B(B[0]), .Y(Y[0]));
    nor_1bit N1 (.A(A[1]), .B(B[1]), .Y(Y[1]));
    nor_1bit N2 (.A(A[2]), .B(B[2]), .Y(Y[2]));
    nor_1bit N3 (.A(A[3]), .B(B[3]), .Y(Y[3]));

endmodule

scr/sumador_1bit.v
module sumador_1bit (
  input A,
  input B,
  input Ci,
  output Co,
  output So
);
  assign Co = ((A & Ci) | (A & B) | (B & Ci)); // Esta es una operacion de AND y OR, Co sera 1 cuando al menos dos entradas sean 1
  assign So = (( A ^ B ^ Ci) ); // Esta es una XOR, So sera 1 cuando un numero impar de entradas sea 1
endmodule

scr/sumador_8bits_1.v
`include "sumador_1bit.v"

module sumador_8bits_1(
    input  [7:0] A, B,
    input        Cin,
    output [7:0] S,
    output       Carry,   // carry final (bit 8)
    output       Ovf      // overflow en complemento a 2
);

    wire [7:0] C;  // wires para los carrys internos

    // Instanciamos los sumadores de 1 bit en cascada
    sumador_1bit FA0 (.A(A[0]), .B(B[0]), .Ci(Cin),  .So(S[0]), .Co(C[0]));
    sumador_1bit FA1 (.A(A[1]), .B(B[1]), .Ci(C[0]), .So(S[1]), .Co(C[1]));
    sumador_1bit FA2 (.A(A[2]), .B(B[2]), .Ci(C[1]), .So(S[2]), .Co(C[2]));
    sumador_1bit FA3 (.A(A[3]), .B(B[3]), .Ci(C[2]), .So(S[3]), .Co(C[3]));
    sumador_1bit FA4 (.A(A[4]), .B(B[4]), .Ci(C[3]), .So(S[4]), .Co(C[4]));
    sumador_1bit FA5 (.A(A[5]), .B(B[5]), .Ci(C[4]), .So(S[5]), .Co(C[5]));
    sumador_1bit FA6 (.A(A[6]), .B(B[6]), .Ci(C[5]), .So(S[6]), .Co(C[6]));
    sumador_1bit FA7 (.A(A[7]), .B(B[7]), .Ci(C[6]), .So(S[7]), .Co(C[7]));

    // El carry final (bit 8 de la suma completa)
    assign Carry = C[7];

    // Overflow en complemento a 2 (cuando los signos de A y B son iguales
    // y el signo del resultado difiere de ellos)
    assign Ovf = (A[7] == B[7]) && (S[7] != A[7]);

endmodule

scr/multiplicador_4bits.v
//`include "sumador_8bits_1.v"

module multiplicador_4bits(
    input  [3:0] A,  // multiplicando
    input  [3:0] B,  // multiplicador
    output [7:0] P   // producto
);
    // Productos parciales
    wire [7:0] PP0, PP1, PP2, PP3;
    wire [7:0] S1, S2, S3;
    wire Carry1, Carry2, Carry3;

    // Generación de productos parciales (cada bit de B multiplica a A)
    assign PP0 = B[0] ? {4'b0000, A}       : 8'b00000000;
    assign PP1 = B[1] ? {3'b000,  A, 1'b0} : 8'b00000000;
    assign PP2 = B[2] ? {2'b00,   A, 2'b00}: 8'b00000000;
    assign PP3 = B[3] ? {1'b0,    A, 3'b000}:8'b00000000;

    // Suma de productos parciales usando el sumador estructural
    sumador_8bits_1 SUM1 (.A(PP0), .B(PP1), .Cin(1'b0), .S(S1), .Carry(Carry1));
    sumador_8bits_1 SUM2 (.A(S1),  .B(PP2), .Cin(1'b0), .S(S2), .Carry(Carry2));
    sumador_8bits_1 SUM3 (.A(S2),  .B(PP3), .Cin(1'b0), .S(S3), .Carry(Carry3));

    // Resultado final
    assign P = S3;

endmodule

scr/restador_8bits_1.v
//`include "sumador_8bits_1.v"

module restador_8bits_1(
    input  [7:0] A, B,
    output [7:0] D,      // Resultado de A - B
    output       Borrow, // Borrow (equivalente al carry, pero para resta)
    output       Ovf     // Overflow en complemento a 2
);

    wire [7:0] B_invertido;
    assign B_invertido = ~B; // complemento a 1 de B

    // Señales internas del sumador
    wire [7:0] S;
    wire Carry;

    // Instanciamos el sumador para hacer A + (~B) + 1
    sumador_8bits_1 SUM_REST (
        .A(A),
        .B(B_invertido),
        .Cin(1'b1),    // sumamos el +1 para complemento a 2
        .S(S),
        .Carry(Carry),
        .Ovf(Ovf)
    );

    // Asignamos las salidas
    assign D = S;
    assign Borrow = ~Carry; // interpretado como "borrow" en la resta

endmodule

scr/ALU_4bits.v
`include "sumador_8bits_1.v"
`include "restador_8bits_1.v"
`include "multiplicador_4bits.v"
`include "nor_4bits.v"

module ALU_4bits (
    input  [3:0] A, B,
    input  [2:0] sel,       // selector de operación
    output reg [7:0] Y,     // resultado
    output reg overflow,    // bandera de overflow
    output reg zero         // bandera de resultado cero
);

    // --- Señales internas ---
    wire [7:0] sum_result, sub_result, mult_result, nor_result;
    wire ovf_sum, ovf_sub;

    // --- Instancias de los módulos estructurales ---

    // SUMA
    sumador_8bits_1 U_sum (
        .A({4'b0000, A}),
        .B({4'b0000, B}),
        .Cin(1'b0),
        .S(sum_result),
        .Carry(),
        .Ovf(ovf_sum)
    );

    // RESTA
    restador_8bits_1 U_sub (
        .A({4'b0000, A}),
        .B({4'b0000, B}),
        .D(sub_result),
        .Borrow(),
        .Ovf(ovf_sub)
    );

    // MULTIPLICACIÓN
    multiplicador_4bits U_mult (
        .A(A),
        .B(B),
        .P(mult_result)
    );

    // NOR
    nor_4bits U_nor (
        .A(A),
        .B(B),
        .Y(nor_result[3:0])
    );
    assign nor_result[7:4] = 4'b0000; // extensión a 8 bits

    // --- Lógica de selección ---
    always @(*) begin
        case (sel)
            3'b000: begin  // Suma
                Y = sum_result;
                overflow = ovf_sum;
            end
            3'b001: begin  // Resta
                Y = sub_result;
                overflow = ovf_sub;
            end
            3'b010: begin  // Multiplicación
                Y = mult_result;
                overflow = 1'b0;
            end
            3'b011: begin  // NOR
                Y = nor_result;
                overflow = 1'b0;
            end
            3'b100: begin  // Desplazamiento a la izquierda
                Y = {4'b0000, A << 1};
                overflow = 1'b0;
            end
            default: begin
                Y = 8'b00000000;
                overflow = 1'b0;
            end
        endcase

        // Bandera de cero
        zero = (Y == 8'b00000000);
    end

endmodule

scr/tb_ALU_4bits.v
`timescale 1ns/1ps
`include "ALU_4bits.v"

module tb_ALU_4bits;

    reg [3:0] A, B;
    reg [2:0] sel;
    wire [7:0] Y;
    wire overflow, zero;

    // Instancia de la ALU
    ALU_4bits uut (
        .A(A),
        .B(B),
        .sel(sel),
        .Y(Y),
        .overflow(overflow),
        .zero(zero)
    );

    // Generación del archivo de simulación
    initial begin
        $dumpfile("ALU_4bits_tb.vcd");
        $dumpvars(0, tb_ALU_4bits);

        // Cabecera de resultados
        $display("-----------------------------------------------------------");
        $display("SEL |   A   |   B   |       Y (Resultado)     | OVF | ZERO ");
        $display("-----------------------------------------------------------");

        // --- SUMA ---
        sel = 3'b000;
        A = 4'd3;  B = 4'd5;  #10; $display("%b | %d | %d | %b (%d) |  %b  |  %b", sel, A, B, Y, Y, overflow, zero);
        A = 4'd15; B = 4'd2;  #10; $display("%b | %d | %d | %b (%d) |  %b  |  %b", sel, A, B, Y, Y, overflow, zero); // overflow esperado
        A = 4'd0;  B = 4'd0;  #10; $display("%b | %d | %d | %b (%d) |  %b  |  %b", sel, A, B, Y, Y, overflow, zero); // suma nula

        // --- RESTA ---
        sel = 3'b001;
        A = 4'd9;  B = 4'd3;  #10; $display("%b | %d | %d | %b (%d) |  %b  |  %b", sel, A, B, Y, Y, overflow, zero);
        A = 4'd3;  B = 4'd9;  #10; $display("%b | %d | %d | %b (%d) |  %b  |  %b", sel, A, B, Y, Y, overflow, zero); // resultado negativo
        A = 4'd8;  B = 4'd8;  #10; $display("%b | %d | %d | %b (%d) |  %b  |  %b", sel, A, B, Y, Y, overflow, zero); // resultado cero

        // --- MULTIPLICACIÓN ---
        sel = 3'b010;
        A = 4'd3;  B = 4'd2;  #10; $display("%b | %d | %d | %b (%d) |  %b  |  %b", sel, A, B, Y, Y, overflow, zero);
        A = 4'd15; B = 4'd15; #10; $display("%b | %d | %d | %b (%d) |  %b  |  %b", sel, A, B, Y, Y, overflow, zero); // producto máximo
        A = 4'd7;  B = 4'd0;  #10; $display("%b | %d | %d | %b (%d) |  %b  |  %b", sel, A, B, Y, Y, overflow, zero); // multiplicar por 0

        // --- NOR ---
        sel = 3'b011;
        A = 4'b0000; B = 4'b0000; #10; $display("%b | %b | %b | %b |  %b  |  %b", sel, A, B, Y[3:0], overflow, zero);
        A = 4'b1111; B = 4'b1111; #10; $display("%b | %b | %b | %b |  %b  |  %b", sel, A, B, Y[3:0], overflow, zero);
        A = 4'b1010; B = 4'b0101; #10; $display("%b | %b | %b | %b |  %b  |  %b", sel, A, B, Y[3:0], overflow, zero);

        // --- DESPLAZAMIENTO IZQ ---
        sel = 3'b100;
        A = 4'b0001; B = 4'bxxxx; #10; $display("%b | %b | ---- | %b |  %b  |  %b", sel, A, Y[3:0], overflow, zero);
        A = 4'b1111; #10; $display("%b | %b | ---- | %b |  %b  |  %b", sel, A, Y[3:0], overflow, zero);

        // --- CASOS LÍMITE ---
        sel = 3'b000; // suma
        A = 4'b1111; B = 4'b1111; #10; $display("%b | %b | %b | %b (%d) |  %b  |  %b", sel, A, B, Y, Y, overflow, zero); // overflow por saturación
        sel = 3'b001; // resta
        A = 4'b0000; B = 4'b1111; #10; $display("%b | %b | %b | %b (%d) |  %b  |  %b", sel, A, B, Y, Y, overflow, zero); // resta con negativo grande

        $display("-----------------------------------------------------------");
        $finish;
    end

endmodule

scr/build/ALU_4bits_tb.vcd
$date
	Wed Oct 15 16:32:21 2025
$end
$version
	Icarus Verilog
$end
$timescale
	1ps
$end
$scope module tb_ALU_4bits $end
$var wire 1 ! zero $end
$var wire 1 " overflow $end
$var wire 8 # Y [7:0] $end
$var reg 4 $ A [3:0] $end
$var reg 4 % B [3:0] $end
$var reg 3 & sel [2:0] $end
$scope module uut $end
$var wire 4 ' A [3:0] $end
$var wire 4 ( B [3:0] $end
$var wire 3 ) sel [2:0] $end
$var wire 8 * sum_result [7:0] $end
$var wire 8 + sub_result [7:0] $end
$var wire 1 , ovf_sum $end
$var wire 1 - ovf_sub $end
$var wire 8 . nor_result [7:0] $end
$var wire 8 / mult_result [7:0] $end
$var reg 8 0 Y [7:0] $end
$var reg 1 " overflow $end
$var reg 1 ! zero $end
$scope module U_mult $end
$var wire 4 1 A [3:0] $end
$var wire 4 2 B [3:0] $end
$var wire 8 3 P [7:0] $end
$var wire 8 4 S3 [7:0] $end
$var wire 8 5 S2 [7:0] $end
$var wire 8 6 S1 [7:0] $end
$var wire 8 7 PP3 [7:0] $end
$var wire 8 8 PP2 [7:0] $end
$var wire 8 9 PP1 [7:0] $end
$var wire 8 : PP0 [7:0] $end
$var wire 1 ; Carry3 $end
$var wire 1 < Carry2 $end
$var wire 1 = Carry1 $end
$scope module SUM1 $end
$var wire 8 > A [7:0] $end
$var wire 8 ? B [7:0] $end
$var wire 1 @ Cin $end
$var wire 1 A Ovf $end
$var wire 8 B S [7:0] $end
$var wire 1 = Carry $end
$var wire 8 C C [7:0] $end
$scope module FA0 $end
$var wire 1 D A $end
$var wire 1 E B $end
$var wire 1 @ Ci $end
$var wire 1 F Co $end
$var wire 1 G So $end
$upscope $end
$scope module FA1 $end
$var wire 1 H A $end
$var wire 1 I B $end
$var wire 1 J Ci $end
$var wire 1 K Co $end
$var wire 1 L So $end
$upscope $end
$scope module FA2 $end
$var wire 1 M A $end
$var wire 1 N B $end
$var wire 1 O Ci $end
$var wire 1 P Co $end
$var wire 1 Q So $end
$upscope $end
$scope module FA3 $end
$var wire 1 R A $end
$var wire 1 S B $end
$var wire 1 T Ci $end
$var wire 1 U Co $end
$var wire 1 V So $end
$upscope $end
$scope module FA4 $end
$var wire 1 W A $end
$var wire 1 X B $end
$var wire 1 Y Ci $end
$var wire 1 Z Co $end
$var wire 1 [ So $end
$upscope $end
$scope module FA5 $end
$var wire 1 \ A $end
$var wire 1 ] B $end
$var wire 1 ^ Ci $end
$var wire 1 _ Co $end
$var wire 1 ` So $end
$upscope $end
$scope module FA6 $end
$var wire 1 a A $end
$var wire 1 b B $end
$var wire 1 c Ci $end
$var wire 1 d Co $end
$var wire 1 e So $end
$upscope $end
$scope module FA7 $end
$var wire 1 f A $end
$var wire 1 g B $end
$var wire 1 h Ci $end
$var wire 1 i Co $end
$var wire 1 j So $end
$upscope $end
$upscope $end
$scope module SUM2 $end
$var wire 8 k A [7:0] $end
$var wire 8 l B [7:0] $end
$var wire 1 m Cin $end
$var wire 1 n Ovf $end
$var wire 8 o S [7:0] $end
$var wire 1 < Carry $end
$var wire 8 p C [7:0] $end
$scope module FA0 $end
$var wire 1 q A $end
$var wire 1 r B $end
$var wire 1 m Ci $end
$var wire 1 s Co $end
$var wire 1 t So $end
$upscope $end
$scope module FA1 $end
$var wire 1 u A $end
$var wire 1 v B $end
$var wire 1 w Ci $end
$var wire 1 x Co $end
$var wire 1 y So $end
$upscope $end
$scope module FA2 $end
$var wire 1 z A $end
$var wire 1 { B $end
$var wire 1 | Ci $end
$var wire 1 } Co $end
$var wire 1 ~ So $end
$upscope $end
$scope module FA3 $end
$var wire 1 !" A $end
$var wire 1 "" B $end
$var wire 1 #" Ci $end
$var wire 1 $" Co $end
$var wire 1 %" So $end
$upscope $end
$scope module FA4 $end
$var wire 1 &" A $end
$var wire 1 '" B $end
$var wire 1 (" Ci $end
$var wire 1 )" Co $end
$var wire 1 *" So $end
$upscope $end
$scope module FA5 $end
$var wire 1 +" A $end
$var wire 1 ," B $end
$var wire 1 -" Ci $end
$var wire 1 ." Co $end
$var wire 1 /" So $end
$upscope $end
$scope module FA6 $end
$var wire 1 0" A $end
$var wire 1 1" B $end
$var wire 1 2" Ci $end
$var wire 1 3" Co $end
$var wire 1 4" So $end
$upscope $end
$scope module FA7 $end
$var wire 1 5" A $end
$var wire 1 6" B $end
$var wire 1 7" Ci $end
$var wire 1 8" Co $end
$var wire 1 9" So $end
$upscope $end
$upscope $end
$scope module SUM3 $end
$var wire 8 :" A [7:0] $end
$var wire 8 ;" B [7:0] $end
$var wire 1 <" Cin $end
$var wire 1 =" Ovf $end
$var wire 8 >" S [7:0] $end
$var wire 1 ; Carry $end
$var wire 8 ?" C [7:0] $end
$scope module FA0 $end
$var wire 1 @" A $end
$var wire 1 A" B $end
$var wire 1 <" Ci $end
$var wire 1 B" Co $end
$var wire 1 C" So $end
$upscope $end
$scope module FA1 $end
$var wire 1 D" A $end
$var wire 1 E" B $end
$var wire 1 F" Ci $end
$var wire 1 G" Co $end
$var wire 1 H" So $end
$upscope $end
$scope module FA2 $end
$var wire 1 I" A $end
$var wire 1 J" B $end
$var wire 1 K" Ci $end
$var wire 1 L" Co $end
$var wire 1 M" So $end
$upscope $end
$scope module FA3 $end
$var wire 1 N" A $end
$var wire 1 O" B $end
$var wire 1 P" Ci $end
$var wire 1 Q" Co $end
$var wire 1 R" So $end
$upscope $end
$scope module FA4 $end
$var wire 1 S" A $end
$var wire 1 T" B $end
$var wire 1 U" Ci $end
$var wire 1 V" Co $end
$var wire 1 W" So $end
$upscope $end
$scope module FA5 $end
$var wire 1 X" A $end
$var wire 1 Y" B $end
$var wire 1 Z" Ci $end
$var wire 1 [" Co $end
$var wire 1 \" So $end
$upscope $end
$scope module FA6 $end
$var wire 1 ]" A $end
$var wire 1 ^" B $end
$var wire 1 _" Ci $end
$var wire 1 `" Co $end
$var wire 1 a" So $end
$upscope $end
$scope module FA7 $end
$var wire 1 b" A $end
$var wire 1 c" B $end
$var wire 1 d" Ci $end
$var wire 1 e" Co $end
$var wire 1 f" So $end
$upscope $end
$upscope $end
$upscope $end
$scope module U_nor $end
$var wire 4 g" A [3:0] $end
$var wire 4 h" B [3:0] $end
$var wire 4 i" Y [3:0] $end
$scope module N0 $end
$var wire 1 j" A $end
$var wire 1 k" B $end
$var wire 1 l" Y $end
$upscope $end
$scope module N1 $end
$var wire 1 m" A $end
$var wire 1 n" B $end
$var wire 1 o" Y $end
$upscope $end
$scope module N2 $end
$var wire 1 p" A $end
$var wire 1 q" B $end
$var wire 1 r" Y $end
$upscope $end
$scope module N3 $end
$var wire 1 s" A $end
$var wire 1 t" B $end
$var wire 1 u" Y $end
$upscope $end
$upscope $end
$scope module U_sub $end
$var wire 8 v" A [7:0] $end
$var wire 8 w" B [7:0] $end
$var wire 8 x" B_invertido [7:0] $end
$var wire 1 y" Borrow $end
$var wire 8 z" D [7:0] $end
$var wire 8 {" S [7:0] $end
$var wire 1 - Ovf $end
$var wire 1 |" Carry $end
$scope module SUM_REST $end
$var wire 8 }" A [7:0] $end
$var wire 8 ~" B [7:0] $end
$var wire 1 !# Cin $end
$var wire 1 - Ovf $end
$var wire 8 "# S [7:0] $end
$var wire 1 |" Carry $end
$var wire 8 ## C [7:0] $end
$scope module FA0 $end
$var wire 1 $# A $end
$var wire 1 %# B $end
$var wire 1 !# Ci $end
$var wire 1 &# Co $end
$var wire 1 '# So $end
$upscope $end
$scope module FA1 $end
$var wire 1 (# A $end
$var wire 1 )# B $end
$var wire 1 *# Ci $end
$var wire 1 +# Co $end
$var wire 1 ,# So $end
$upscope $end
$scope module FA2 $end
$var wire 1 -# A $end
$var wire 1 .# B $end
$var wire 1 /# Ci $end
$var wire 1 0# Co $end
$var wire 1 1# So $end
$upscope $end
$scope module FA3 $end
$var wire 1 2# A $end
$var wire 1 3# B $end
$var wire 1 4# Ci $end
$var wire 1 5# Co $end
$var wire 1 6# So $end
$upscope $end
$scope module FA4 $end
$var wire 1 7# A $end
$var wire 1 8# B $end
$var wire 1 9# Ci $end
$var wire 1 :# Co $end
$var wire 1 ;# So $end
$upscope $end
$scope module FA5 $end
$var wire 1 <# A $end
$var wire 1 =# B $end
$var wire 1 ># Ci $end
$var wire 1 ?# Co $end
$var wire 1 @# So $end
$upscope $end
$scope module FA6 $end
$var wire 1 A# A $end
$var wire 1 B# B $end
$var wire 1 C# Ci $end
$var wire 1 D# Co $end
$var wire 1 E# So $end
$upscope $end
$scope module FA7 $end
$var wire 1 F# A $end
$var wire 1 G# B $end
$var wire 1 H# Ci $end
$var wire 1 I# Co $end
$var wire 1 J# So $end
$upscope $end
$upscope $end
$upscope $end
$scope module U_sum $end
$var wire 8 K# A [7:0] $end
$var wire 8 L# B [7:0] $end
$var wire 1 M# Cin $end
$var wire 1 , Ovf $end
$var wire 8 N# S [7:0] $end
$var wire 1 O# Carry $end
$var wire 8 P# C [7:0] $end
$scope module FA0 $end
$var wire 1 Q# A $end
$var wire 1 R# B $end
$var wire 1 M# Ci $end
$var wire 1 S# Co $end
$var wire 1 T# So $end
$upscope $end
$scope module FA1 $end
$var wire 1 U# A $end
$var wire 1 V# B $end
$var wire 1 W# Ci $end
$var wire 1 X# Co $end
$var wire 1 Y# So $end
$upscope $end
$scope module FA2 $end
$var wire 1 Z# A $end
$var wire 1 [# B $end
$var wire 1 \# Ci $end
$var wire 1 ]# Co $end
$var wire 1 ^# So $end
$upscope $end
$scope module FA3 $end
$var wire 1 _# A $end
$var wire 1 `# B $end
$var wire 1 a# Ci $end
$var wire 1 b# Co $end
$var wire 1 c# So $end
$upscope $end
$scope module FA4 $end
$var wire 1 d# A $end
$var wire 1 e# B $end
$var wire 1 f# Ci $end
$var wire 1 g# Co $end
$var wire 1 h# So $end
$upscope $end
$scope module FA5 $end
$var wire 1 i# A $end
$var wire 1 j# B $end
$var wire 1 k# Ci $end
$var wire 1 l# Co $end
$var wire 1 m# So $end
$upscope $end
$scope module FA6 $end
$var wire 1 n# A $end
$var wire 1 o# B $end
$var wire 1 p# Ci $end
$var wire 1 q# Co $end
$var wire 1 r# So $end
$upscope $end
$scope module FA7 $end
$var wire 1 s# A $end
$var wire 1 t# B $end
$var wire 1 u# Ci $end
$var wire 1 v# Co $end
$var wire 1 w# So $end
$upscope $end
$upscope $end
$upscope $end
$upscope $end
$enddefinitions $end
$comment Show the parameter values. $end
$dumpall
$end
#0
$dumpvars
0w#
0v#
0u#
0t#
0s#
0r#
0q#
0p#
0o#
0n#
0m#
0l#
0k#
0j#
0i#
0h#
0g#
0f#
0e#
0d#
1c#
0b#
1a#
0`#
0_#
0^#
1]#
1\#
1[#
0Z#
0Y#
1X#
1W#
0V#
1U#
0T#
1S#
1R#
1Q#
b111 P#
0O#
b1000 N#
0M#
b101 L#
b11 K#
1J#
0I#
0H#
1G#
0F#
1E#
0D#
0C#
1B#
0A#
1@#
0?#
0>#
1=#
0<#
1;#
0:#
09#
18#
07#
16#
05#
04#
13#
02#
11#
00#
1/#
0.#
0-#
1,#
1+#
1*#
1)#
1(#
0'#
1&#
0%#
1$#
b11 ##
b11111110 "#
1!#
b11111010 ~"
b11 }"
0|"
b11111110 {"
b11111110 z"
1y"
b11111010 x"
b101 w"
b11 v"
1u"
0t"
0s"
0r"
1q"
0p"
0o"
0n"
1m"
0l"
1k"
1j"
b1000 i"
b101 h"
b11 g"
0f"
0e"
0d"
0c"
0b"
0a"
0`"
0_"
0^"
0]"
0\"
0["
0Z"
0Y"
0X"
0W"
0V"
0U"
0T"
0S"
1R"
0Q"
0P"
0O"
1N"
1M"
0L"
0K"
0J"
1I"
1H"
0G"
0F"
0E"
1D"
1C"
0B"
0A"
1@"
b0 ?"
b1111 >"
0="
0<"
b0 ;"
b1111 :"
09"
08"
07"
06"
05"
04"
03"
02"
01"
00"
0/"
0."
0-"
0,"
0+"
0*"
0)"
0("
0'"
0&"
1%"
0$"
0#"
1""
0!"
1~
0}
0|
1{
0z
1y
0x
0w
0v
1u
1t
0s
0r
1q
b0 p
b1111 o
0n
0m
b1100 l
b11 k
0j
0i
0h
0g
0f
0e
0d
0c
0b
0a
0`
0_
0^
0]
0\
0[
0Z
0Y
0X
0W
0V
0U
0T
0S
0R
0Q
0P
0O
0N
0M
1L
0K
0J
0I
1H
1G
0F
0E
1D
b0 C
b11 B
0A
0@
b0 ?
b11 >
0=
0<
0;
b11 :
b0 9
b1100 8
b0 7
b11 6
b1111 5
b1111 4
b1111 3
b101 2
b11 1
b1000 0
b1111 /
b1000 .
0-
0,
b11111110 +
b1000 *
b0 )
b101 (
b11 '
b0 &
b101 %
b11 $
b1000 #
0"
0!
$end
#10000
0y"
1|"
1I#
0J#
1H#
1D#
0E#
0C"
1C#
1?#
0@"
0@#
0t
1M"
1R"
1>#
1:#
1W"
b11110 /
b11110 3
b11110 4
b11110 >"
0\"
0q
1&"
1I"
1N"
1h#
0;#
0W#
0G
1[
1~
1%"
1f#
14#
19#
1z
1!"
1S"
0X"
0S#
1'#
0,#
b1110 P#
1b#
10#
b11111111 ##
15#
1Q
b11110 6
b11110 B
b11110 k
1V
1*"
b11110 5
b11110 o
b11110 :"
0/"
b10001 #
b10001 0
1T#
0Y#
0D
0H
1I
1N
1S
1X
0{
0""
b10001 *
b10001 N#
0c#
11#
b1101 +
b1101 z"
b1101 {"
b1101 "#
16#
b0 .
b0 i"
0u"
1%#
0)#
1.#
b11110 9
b11110 ?
0M
0R
0'"
0,"
0R#
1V#
0[#
b11111101 x"
b11111101 ~"
0k"
1n"
0q"
1Z#
1_#
1-#
12#
b0 :
b0 >
b0 8
b0 l
1p"
1s"
b10 L#
b10 w"
b10 %
b10 (
b10 2
b10 h"
b1111 K#
b1111 v"
b1111 }"
b1111 $
b1111 '
b1111 1
b1111 g"
#20000
0H"
0M"
0R"
b0 /
b0 3
b0 4
b0 >"
0W"
0D"
0I"
0N"
0S"
1!
0y
0~
0%"
b0 5
b0 o
b0 :"
0*"
0h#
0\#
0a#
0f#
0u
0z
0!"
0&"
0X#
0]#
b0 P#
0b#
0L
0Q
0V
b0 6
b0 B
b0 k
0[
b0 #
b0 0
0T#
0^#
b0 *
b0 N#
0c#
0'#
0,#
01#
b0 +
b0 z"
b0 {"
b0 "#
06#
1l"
1o"
1r"
b1111 .
b1111 i"
1u"
1)#
0I
0N
0S
0X
0V#
b11111111 x"
b11111111 ~"
0n"
0Q#
0U#
0Z#
0_#
0$#
0(#
0-#
02#
b0 9
b0 ?
0j"
0m"
0p"
0s"
b0 L#
b0 w"
b0 %
b0 (
b0 2
b0 h"
b0 K#
b0 v"
b0 }"
b0 $
b0 '
b0 1
b0 g"
#30000
1C"
1R"
1H"
b11011 /
b11011 3
b11011 4
b11011 >"
1W"
1@"
1N"
1D"
1S"
1^#
04#
1t
1%"
1y
b11011 5
b11011 o
b11011 :"
1*"
1\#
00#
1X#
11#
1q
1!"
1u
1&"
0/#
1G
1V
1L
b11011 6
b11011 B
b11011 k
1[
1W#
b11111001 ##
0+#
1,#
b11 P#
1S#
0!
b110 #
b110 0
0Y#
1D
1R
1I
1X
0o"
b1100 *
b1100 N#
1c#
0'#
b110 +
b110 z"
b110 {"
b110 "#
06#
0l"
b100 .
b100 i"
0u"
0%#
0)#
b1001 :
b1001 >
b10010 9
b10010 ?
1R#
1V#
b11111100 x"
b11111100 ~"
1k"
1n"
1Q#
1_#
1$#
12#
1j"
1s"
b11 L#
b11 w"
b11 %
b11 (
b11 2
b11 h"
b1001 K#
b1001 v"
b1001 }"
b1001 $
b1001 '
b1001 1
b1001 g"
b1 &
b1 )
#40000
1y"
0|"
0I#
1J#
0H#
0D#
1E#
0C#
0?#
1H"
0M"
1@#
0\"
14#
0>#
1D"
0N"
0I"
0S"
0U"
0Z"
10#
0:#
1y
0%"
0~
b11 5
b11 o
b11 :"
0*"
0Q"
b0 ?"
0V"
01#
1;#
0O
1R"
b11011 /
b11011 3
b11011 4
b11011 >"
1W"
1/#
09#
b0 C
0K
1u
0!"
0z
0&"
1+#
b111 ##
05#
b11111010 #
b11111010 0
1L
0V
0Q
b11 6
b11 B
b11 k
0[
0I
1O"
1T"
1,#
b11111010 +
b11111010 z"
b11111010 {"
b11111010 "#
16#
1)#
03#
b11000 7
b11000 ;"
1H
0R
0N
0X
0V#
1`#
b11110110 x"
b11110110 ~"
0n"
1t"
1U#
0_#
1(#
02#
b11 :
b11 >
b0 9
b0 ?
1m"
0s"
b1001 L#
b1001 w"
b1001 %
b1001 (
b1001 2
b1001 h"
b11 K#
b11 v"
b11 }"
b11 $
b11 '
b11 1
b11 g"
#50000
0y"
1|"
1I#
1!
0J#
1H#
1D#
0E#
1C#
1?#
0C"
0H"
0@#
1>#
0@"
0D"
0N"
1:#
0t
0y
b0 5
b0 o
b0 :"
0%"
0^#
1h#
0;#
0W#
0\#
1f#
19#
0q
0u
0!"
0S#
0X#
b1000 P#
1b#
b11111111 ##
15#
0G
0L
b0 6
b0 B
b0 k
0V
0R"
0W"
b1000000 /
b1000000 3
b1000000 4
b1000000 >"
1a"
b0 #
b0 0
0Y#
b10000 *
b10000 N#
0c#
0'#
0,#
b0 +
b0 z"
b0 {"
b0 "#
06#
1l"
b111 .
b111 i"
1o"
1%#
0D
0H
0R
0O"
0T"
1^"
0R#
b11110111 x"
b11110111 ~"
0k"
0Q#
0U#
1_#
0$#
0(#
12#
b0 :
b0 >
b1000000 7
b1000000 ;"
0j"
0m"
1s"
b1000 L#
b1000 w"
b1000 %
b1000 (
b1000 2
b1000 h"
b1000 K#
b1000 v"
b1000 }"
b1000 $
b1000 '
b1000 1
b1000 g"
#60000
1H"
1M"
1D"
1I"
1y
b110 5
b110 o
b110 :"
1~
1u
1z
1^#
0h#
1L
b110 6
b110 B
b110 k
1Q
1\#
0f#
1X#
b10 P#
0b#
0R"
0W"
b110 /
b110 3
b110 4
b110 >"
0a"
1I
1N
b101 *
b101 N#
1T#
1'#
0,#
b1 +
b1 z"
b1 {"
b1 "#
06#
0l"
0o"
b1100 .
b1100 i"
1u"
0)#
13#
b110 9
b110 ?
0O"
0T"
0^"
1V#
0`#
b11111101 x"
b11111101 ~"
1n"
0t"
1Q#
1U#
0_#
1$#
1(#
02#
b0 7
b0 ;"
1j"
1m"
0s"
0!
b110 #
b110 0
b10 L#
b10 w"
b10 %
b10 (
b10 2
b10 h"
b11 K#
b11 v"
b11 }"
b11 $
b11 '
b11 1
b11 g"
b10 &
b10 )
#70000
1="
1f"
1]"
1d"
14"
1+"
1`"
12"
1C"
0H"
1`
1."
1^
1U"
1Z"
1_"
1@"
0D"
1Z
1Q"
1V"
b1111000 ?"
1["
1("
1-"
1t
0y
0M"
1$"
1)"
1O
1T
1Y
1#"
1Y#
1q
1K
0u
1P
1z
b11110 C
1U
b111100 p
1}
0I"
1N"
0S"
1X"
1h#
1W#
1c#
b11100001 #
b11100001 0
1G
0L
1Q
0~
1%"
0*"
b1101001 5
b1101001 o
b1101001 :"
1/"
0R"
0W"
1\"
b11100001 /
b11100001 3
b11100001 4
b11100001 >"
1a"
1f#
1!"
0&"
1S#
1a#
0'#
1b#
1V
b101101 6
b101101 B
b101101 k
0[
b11110 *
b11110 N#
0T#
b1111 P#
1]#
1D
1H
1M
1R
1{
1""
1'"
1,"
1O"
1T"
1Y"
1^"
01#
b0 +
b0 z"
b0 {"
b0 "#
06#
0r"
b0 .
b0 i"
0u"
0%#
0.#
03#
b1111 :
b1111 >
b111100 8
b111100 l
b1111000 7
b1111000 ;"
1S
1X
1R#
1[#
1`#
b11110000 x"
b11110000 ~"
1k"
1q"
1t"
1Z#
1_#
1-#
12#
b11110 9
b11110 ?
1p"
1s"
b1111 L#
b1111 w"
b1111 %
b1111 (
b1111 2
b1111 h"
b1111 K#
b1111 v"
b1111 }"
b1111 $
b1111 '
b1111 1
b1111 g"
